spwge/__init__.py
spwge-0.1.dist-info/LICENSE.txt
spwge-0.1.dist-info/METADATA
spwge-0.1.dist-info/WHEEL
spwge-0.1.dist-info/top_level.txt
spwge-0.1.dist-info/RECORD
