Metadata-Version: 2.1
Name: spwge
Version: 0.1
Summary: This is a python package to generate random passwords
Home-page: UNKNOWN
Author: SaiReventh
Author-email: saireventhsr@gmail.com
License: UNKNOWN
Platform: UNKNOWN
Classifier: Programming Language :: Python :: 3
Classifier: License :: OSI Approved :: MIT License
Classifier: Operating System :: OS Independent
License-File: LICENSE.txt
